pandas_dedupe/__init__.py
pandas_dedupe/dedupe_dataframe.py
pandas_dedupe/gazetteer_dataframe.py
pandas_dedupe/link_dataframes.py
pandas_dedupe/utility_functions.py
pandas_dedupe-1.5.0.dist-info/METADATA
pandas_dedupe-1.5.0.dist-info/WHEEL
pandas_dedupe-1.5.0.dist-info/top_level.txt
pandas_dedupe-1.5.0.dist-info/RECORD
