Metadata-Version: 2.1
Name: pandas_dedupe
Version: 1.5.0
Summary: The Dedupe library made easy with Pandas.
Home-page: https://github.com/Lyonk71/pandas-dedupe
Author: Keith Lyons
Author-email: lyonk71@gmail.com
License: MIT
Platform: UNKNOWN
